elvis_repl/__init__.py
elvis_repl/core.py
elvis_repl-0.1.1.dist-info/LICENSE
elvis_repl-0.1.1.dist-info/METADATA
elvis_repl-0.1.1.dist-info/WHEEL
elvis_repl-0.1.1.dist-info/top_level.txt
elvis_repl-0.1.1.dist-info/RECORD
