Metadata-Version: 2.1
Name: elvis-repl
Version: 0.1.1
Summary: Elvis has left the building - A REPL template engine that remembers
Author-email: Kaspar Kallas <kaspar.kana.kallas@gmail.com>
License: BSD-3-Clause
Project-URL: Homepage, https://github.com/KKallas/elvis
Project-URL: Bug Tracker, https://github.com/KKallas/elvis/issues
Keywords: repl,template,development,jupyter
Classifier: Development Status :: 4 - Beta
Classifier: Environment :: Console
Classifier: Framework :: IPython
Classifier: Framework :: Jupyter
Classifier: Intended Audience :: Developers
Classifier: License :: OSI Approved :: BSD License
Classifier: Operating System :: OS Independent
Classifier: Programming Language :: Python :: 3
Classifier: Programming Language :: Python :: 3.7
Classifier: Programming Language :: Python :: 3.8
Classifier: Programming Language :: Python :: 3.9
Classifier: Programming Language :: Python :: 3.10
Classifier: Topic :: Software Development :: Libraries :: Python Modules
Requires-Python: >=3.7
License-File: LICENSE
Provides-Extra: jupyter
Requires-Dist: ipython; extra == "jupyter"
Provides-Extra: test
Requires-Dist: pytest>=6.0; extra == "test"
